compoctl
