Metadata-Version: 2.1
Name: compoctl
Version: 0.2.1.post3
Summary: Wrap docker-compose to acheive dev-perfect CI
Home-page: https://yourlabs.io/oss/compoctl
Author: James Pic
Author-email: jamespic@gmail.com
License: UNKNOWN
Platform: UNKNOWN
